sier2_blocks/blocks/__init__.py
sier2_blocks/blocks/holoviews.py
sier2_blocks/blocks/io.py
sier2_blocks/blocks/list_helper.py
sier2_blocks/blocks/test_data.py
sier2_blocks/blocks/view.py
sier2_blocks/dags/__init__.py
sier2_blocks/dags/examples.py
sier2_blocks/shelf/__init__.py
sier2_blocks-0.13.dist-info/LICENSE
sier2_blocks-0.13.dist-info/METADATA
sier2_blocks-0.13.dist-info/WHEEL
sier2_blocks-0.13.dist-info/entry_points.txt
sier2_blocks-0.13.dist-info/RECORD
