Metadata-Version: 2.3
Name: sier2-blocks
Version: 0.13
Summary: Blocks for sier2
Author: Algol60
Author-email: algol60 <algol60@users.noreply.github.com>
Classifier: Programming Language :: Python :: 3.11
Classifier: Operating System :: OS Independent
Classifier: Intended Audience :: Science/Research
Classifier: Intended Audience :: Developers
Classifier: Topic :: Scientific/Engineering
Classifier: Topic :: Software Development :: Libraries
Provides-Extra: all
Provides-Extra: faker
Provides-Extra: vis
Requires-Dist: faker ; extra == "all"
Requires-Dist: faker ; extra == "faker"
Requires-Dist: holoviews (>=1.19.0,<1.20.0) ; extra == "all"
Requires-Dist: holoviews (>=1.19.0,<1.20.0) ; extra == "vis"
